.coveragerc
.git_archival.txt
.gitattributes
.gitignore
.readthedocs.yml
CHANGES.rst
LICENSE.rst
README.rst
pyproject.toml
requirements.txt
setup.cfg
setup.py
.github/dependabot.yml
.github/workflows/linting.yaml
.github/workflows/mock_generation_test.yaml
.github/workflows/monthly-warning-test.yaml
.github/workflows/shape_optimization.yaml
.github/workflows/test_latest_releases.yaml
.github/workflows/test_main_branch.yaml
.github/workflows/test_new_diffstar.yaml
.github/workflows/tests_cron.yaml
diffsky/__init__.py
diffsky/_version.py
diffsky/diffndhist.py
diffsky/mc_diffsky.py
diffsky/phot_utils.py
diffsky/sbl18_photgrad.py
diffsky/tw_photgrad.py
diffsky.egg-info/PKG-INFO
diffsky.egg-info/SOURCES.txt
diffsky.egg-info/dependency_links.txt
diffsky.egg-info/requires.txt
diffsky.egg-info/top_level.txt
diffsky/burstpop/__init__.py
diffsky/burstpop/diffburstpop.py
diffsky/burstpop/diffqburstpop.py
diffsky/burstpop/diffqburstpop_mono.py
diffsky/burstpop/diffqburstpop_mono_noise.py
diffsky/burstpop/fburstpop.py
diffsky/burstpop/fburstpop_mono.py
diffsky/burstpop/freqburst.py
diffsky/burstpop/freqburst_mono.py
diffsky/burstpop/tburstpop.py
diffsky/burstpop/diagnostics/__init__.py
diffsky/burstpop/diagnostics/plot_fburstpop.py
diffsky/burstpop/diagnostics/plot_tburstpop.py
diffsky/burstpop/diagnostics/tests/__init__.py
diffsky/burstpop/diagnostics/tests/test_plot_fburstpop.py
diffsky/burstpop/diagnostics/tests/test_plot_tburstpop.py
diffsky/burstpop/tests/__init__.py
diffsky/burstpop/tests/test_diffburstpop.py
diffsky/burstpop/tests/test_diffqburstpop.py
diffsky/burstpop/tests/test_diffqburstpop_mono.py
diffsky/burstpop/tests/test_diffqburstpop_mono_noise.py
diffsky/burstpop/tests/test_fburstpop.py
diffsky/burstpop/tests/test_fburstpop_mono.py
diffsky/burstpop/tests/test_freqburst.py
diffsky/burstpop/tests/test_freqburst_mono.py
diffsky/burstpop/tests/test_tburstpop.py
diffsky/cosmos_utils/__init__.py
diffsky/cosmos_utils/cosmos_mstar_model.py
diffsky/cosmos_utils/tests/__init__.py
diffsky/cosmos_utils/tests/test_cosmos_mstar_model.py
diffsky/data_loaders/__init__.py
diffsky/data_loaders/cosmos20_loader.py
