Metadata-Version: 2.4
Name: diffsky
Version: 0.3.3
Summary: Library for differentiable generation of synthetic skies
Author-email: Andrew Hearin <ahearin@anl.gov>
License: BSD 3-Clause License
Project-URL: home, https://github.com/ArgonneCPAC/diffsky
Classifier: Programming Language :: Python :: 3
Requires-Python: >=3.11
License-File: LICENSE.rst
Requires-Dist: numpy
Requires-Dist: jax
Requires-Dist: diffmah>=0.7.3
Requires-Dist: diffstar>=1.0.1
Requires-Dist: dsps>=0.4.5
Requires-Dist: h5py
Dynamic: license-file
